[
  {
    "name": "admin",
    "path": "/admin",
    "component": "D:\\\\git\\\\evi-shop\\\\pages\\\\admin\\\\index.vue",
    "chunkName": "pages/admin/index",
    "_name": "_1d80b524"
  },
  {
    "name": "cart",
    "path": "/cart",
    "component": "D:\\\\git\\\\evi-shop\\\\pages\\\\cart.vue",
    "chunkName": "pages/cart",
    "_name": "_41a40c2a"
  },
  {
    "name": "login",
    "path": "/login",
    "component": "D:\\\\git\\\\evi-shop\\\\pages\\\\login.vue",
    "chunkName": "pages/login",
    "_name": "_d3f620a4"
  },
  {
    "name": "admin-editor",
    "path": "/admin/editor",
    "component": "D:\\\\git\\\\evi-shop\\\\pages\\\\admin\\\\editor.vue",
    "chunkName": "pages/admin/editor",
    "_name": "_9fef99fe"
  },
  {
    "name": "index",
    "path": "/",
    "component": "D:\\\\git\\\\evi-shop\\\\pages\\\\index.vue",
    "chunkName": "pages/index",
    "_name": "_674566d2"
  }
]
